hi_mangg907/__init__.py
hi_mangg907/hello.py
hi_mangG907-0.8.0.dist-info/METADATA
hi_mangG907-0.8.0.dist-info/WHEEL
hi_mangG907-0.8.0.dist-info/entry_points.txt
hi_mangG907-0.8.0.dist-info/top_level.txt
hi_mangG907-0.8.0.dist-info/RECORD
