Metadata-Version: 2.1
Name: hi_mangG907
Version: 0.8.0
Summary: Default template for PDM package
Author-email: mangG907 <mang.gee@gmail.com>
License: MIT
Requires-Python: ==3.12.*
